flashboot_core/__init__.py
flashboot_core/env/__init__.py
flashboot_core/env/environment.py
flashboot_core/env/properties_property_source_loader.py
flashboot_core/env/property_source.py
flashboot_core/env/property_source_loader.py
flashboot_core/env/yaml_property_source_loader.py
flashboot_core/event_bus/__init__.py
flashboot_core/event_bus/async_event_bus.py
flashboot_core/event_bus/base.py
flashboot_core/event_bus/sync_event_bus.py
flashboot_core/exceptions/__init__.py
flashboot_core/exceptions/base.py
flashboot_core/exceptions/event_bus.py
flashboot_core/io/__init__.py
flashboot_core/io/file.py
flashboot_core/io/file_system_resource.py
flashboot_core/io/resource.py
flashboot_core/utils/__init__.py
flashboot_core/utils/project_utils.py
flashboot_core-0.1.23.dist-info/METADATA
flashboot_core-0.1.23.dist-info/WHEEL
flashboot_core-0.1.23.dist-info/top_level.txt
flashboot_core-0.1.23.dist-info/RECORD
