Metadata-Version: 2.4
Name: flashboot-core
Version: 0.1.23
Summary: A springboot likely framework for python.
Requires-Python: >=3.10
Requires-Dist: commons-lang>=0.2.13
Requires-Dist: loguru>=0.7.3
Requires-Dist: pydantic>=2.11.4
Requires-Dist: pydantic-yaml>=1.4.0
Requires-Dist: pyyaml>=6.0.2
